ultraloglog-0.1.4.dist-info/METADATA
ultraloglog-0.1.4.dist-info/WHEEL
ultraloglog-0.1.4.dist-info/licenses/LICENSE
ultraloglog/__init__.py
ultraloglog/ultraloglog.cpython-311-x86_64-linux-gnu.so
ultraloglog-0.1.4.dist-info/RECORD
