Metadata-Version: 2.4
Name: ultraloglog
Version: 0.1.4
Classifier: Development Status :: 4 - Beta
Classifier: Intended Audience :: Developers
Classifier: License :: OSI Approved :: Apache Software License
Classifier: Programming Language :: Python :: 3
Classifier: Programming Language :: Python :: 3.8
Classifier: Programming Language :: Python :: 3.9
Classifier: Programming Language :: Python :: 3.10
Classifier: Programming Language :: Python :: 3.11
Classifier: Programming Language :: Python :: 3.12
Classifier: Programming Language :: Python :: 3.13
Classifier: Programming Language :: Rust
Classifier: Topic :: Scientific/Engineering
Classifier: Topic :: Software Development :: Libraries :: Python Modules
License-File: LICENSE
Summary: Python bindings for UltraLogLog, a space-efficient alternative to HyperLogLog for approximate distinct counting
Keywords: ultraloglog,algorithm,sketch,probabilistic,hyperloglog
Author: Ruihang Xia <waynestxia@gmail.com>, Jianshu Zhao <jianshuzhao@yahoo.com>
Author-email: Ruihang Xia <waynestxia@gmail.com>, Jianshu Zhao <jianshuzhao@yahoo.com>
License: Apache-2.0
Requires-Python: >=3.8
Project-URL: Homepage, https://github.com/waynexia/ultraloglog
Project-URL: Repository, https://github.com/waynexia/ultraloglog
Project-URL: Documentation, https://github.com/waynexia/ultraloglog/blob/master/README.md
